nginx_push_stream/__init__.py
nginx_push_stream/auth.py
nginx_push_stream/const.py
nginx_push_stream/context_processors.py
nginx_push_stream/core.py
nginx_push_stream/tests.py
nginx_push_stream/conf/__init__.py
nginx_push_stream/conf/settings.py
nginx_push_stream/management/__init__.py
nginx_push_stream/management/commands/__init__.py
nginx_push_stream/management/commands/publish_message.py
nginx_push_stream/static/nginx_push_stream/js/pushstream.js
django_nginx_push_stream-0.0.1.dist-info/LICENSE
django_nginx_push_stream-0.0.1.dist-info/METADATA
django_nginx_push_stream-0.0.1.dist-info/WHEEL
django_nginx_push_stream-0.0.1.dist-info/top_level.txt
django_nginx_push_stream-0.0.1.dist-info/RECORD
