Metadata-Version: 2.1
Name: django-nginx-push-stream
Version: 0.0.1
Summary: nginx with http-push-stream module support for Django
Home-page: https://github.com/mpasternak/django-nginx-push-stream
Author: Michał Pasternak
Author-email: michal.dtz@gmail.com
License: MIT license
Platform: UNKNOWN
Classifier: Development Status :: 2 - Pre-Alpha
Classifier: Intended Audience :: Developers
Classifier: License :: OSI Approved :: MIT License
Classifier: Natural Language :: English
Classifier: Programming Language :: Python :: 3.7
Requires-Dist: Django
